django_friendships-1.0.3.dist-info/DESCRIPTION.rst
django_friendships-1.0.3.dist-info/METADATA
django_friendships-1.0.3.dist-info/RECORD
django_friendships-1.0.3.dist-info/WHEEL
django_friendships-1.0.3.dist-info/metadata.json
django_friendships-1.0.3.dist-info/top_level.txt
friendship/__init__.py
friendship/apps.py
friendship/models.py
friendship/test_friendships.py
