Metadata-Version: 2.0
Name: django-friendships
Version: 1.0.3
Summary: Simple solution for Django User Friendships
Home-page: https://github.com/Aperyon/django-friendships
Author: Zoltan Kohalmy
Author-email: zoltankohalmy@gmail.com
License: UNKNOWN
Platform: UNKNOWN
